wigtools/__init__.py
wigtools/__main__.py
wigtools/functional.py
wigtools/wiggle.py
wigtools-0.0.1.dist-info/entry_points.txt
wigtools-0.0.1.dist-info/LICENSE
wigtools-0.0.1.dist-info/WHEEL
wigtools-0.0.1.dist-info/METADATA
wigtools-0.0.1.dist-info/RECORD
