Metadata-Version: 2.1
Name: wigtools
Version: 0.0.1
Summary: A set of tools for wiggle file
Home-page: https://github.com/pwwang/wigtools
License: MIT
Author: pwwang
Author-email: pwwang@pwwang.com
Requires-Python: >=3.6,<4.0
Classifier: License :: OSI Approved :: MIT License
Classifier: Programming Language :: Python :: 3
Classifier: Programming Language :: Python :: 3.6
Classifier: Programming Language :: Python :: 3.7
Classifier: Programming Language :: Python :: 3.8
Requires-Dist: attrs
Requires-Dist: diot
Requires-Dist: pyparam
Project-URL: Repository, https://github.com/pwwang/wigtools
